rela_transformer/__init__.py
rela_transformer/autoregressive_wrapper.py
rela_transformer/rela_transformer.py
rela_transformer-0.0.7.dist-info/LICENSE
rela_transformer-0.0.7.dist-info/METADATA
rela_transformer-0.0.7.dist-info/WHEEL
rela_transformer-0.0.7.dist-info/top_level.txt
rela_transformer-0.0.7.dist-info/RECORD
